{
  "meta": {
    "build": {
      "build-date": "2021-05-27",
      "codified-date": "2020-03-30",
      "platform": {
        "reproducible": "true",
        "version": "2.2.1"
      },
      "repositories": [
        {
          "commit": "6a494db1660e977cbf5e0cfa51b0db9dd0a22dee",
          "name": "cityofsanmateo/law-xml"
        },
        {
          "commit": "342daaaef2aa33051b39a3762c11d5ba3b15d573",
          "name": "cityofsanmateo/law-xml-codified"
        }
      ]
    },
    "canonical-urls": {
      "html": "https://sanmateo.ca.us.open.law",
      "html-bulk": "https://github.com/cityofsanmateo/law-html",
      "static-assets": "https://github.com/openlawlibrary/law-static-assets",
      "xml-bulk": "https://github.com/cityofsanmateo/law-xml"
    },
    "contact": {
      "email": "help@openlawlib.org"
    },
    "description": "Browse the laws and code of San Mateo",
    "history-start": "2018-03-05"
  }
}